taggit_autosuggest/__init__.py
taggit_autosuggest/managers.py
taggit_autosuggest/models.py
taggit_autosuggest/urls.py
taggit_autosuggest/utils.py
taggit_autosuggest/views.py
taggit_autosuggest/widgets.py
taggit_autosuggest/locale/de/LC_MESSAGES/django.mo
taggit_autosuggest/locale/de/LC_MESSAGES/django.po
taggit_autosuggest/locale/fr/LC_MESSAGES/django.mo
taggit_autosuggest/locale/fr/LC_MESSAGES/django.po
taggit_autosuggest/locale/pt_BR/LC_MESSAGES/django.mo
taggit_autosuggest/locale/pt_BR/LC_MESSAGES/django.po
taggit_autosuggest/static/jquery-autosuggest/css/autoSuggest-grappelli.css
taggit_autosuggest/static/jquery-autosuggest/css/autoSuggest.css
taggit_autosuggest/static/jquery-autosuggest/js/jquery.autoSuggest.minified.js
django_taggit_autosuggest-0.4.2.dist-info/LICENCE
django_taggit_autosuggest-0.4.2.dist-info/METADATA
django_taggit_autosuggest-0.4.2.dist-info/WHEEL
django_taggit_autosuggest-0.4.2.dist-info/top_level.txt
django_taggit_autosuggest-0.4.2.dist-info/RECORD
