Metadata-Version: 2.2
Name: django-taggit-autosuggest
Version: 0.4.2
Summary: Autosuggestions for django-taggit
Home-page: https://bitbucket.org/fabian/django-taggit-autosuggest
Author: Fabian Topfstedt
Author-email: topfstedt@schneevonmorgen.com
Classifier: Development Status :: 4 - Beta
Classifier: Environment :: Web Environment
Classifier: Intended Audience :: Developers
Classifier: License :: OSI Approved :: MIT License
Classifier: Operating System :: OS Independent
Classifier: Programming Language :: Python
Classifier: Framework :: Django
License-File: LICENCE
Requires-Dist: django-taggit
Dynamic: author
Dynamic: author-email
Dynamic: classifier
Dynamic: description
Dynamic: home-page
Dynamic: requires-dist
Dynamic: summary
